{
  "AWSTemplateFormatVersion": "2010-09-09",
  "Description": "The AWS CloudFormation template for this Serverless application",
  "Resources": {
    "ServerlessDeploymentBucket": {
      "Type": "AWS::S3::Bucket"
    },
    "IamRoleLambdaExecution": {
      "Type": "AWS::IAM::Role",
      "Properties": {
        "AssumeRolePolicyDocument": {
          "Version": "2012-10-17",
          "Statement": [
            {
              "Effect": "Allow",
              "Principal": {
                "Service": [
                  "lambda.amazonaws.com"
                ]
              },
              "Action": [
                "sts:AssumeRole"
              ]
            }
          ]
        },
        "Path": "/"
      }
    },
    "IamPolicyLambdaExecution": {
      "Type": "AWS::IAM::Policy",
      "Properties": {
        "PolicyName": "dev-serverless-mailer-rc2-lambda",
        "PolicyDocument": {
          "Version": "2012-10-17",
          "Statement": [
            {
              "Effect": "Allow",
              "Action": [
                "logs:CreateLogGroup",
                "logs:CreateLogStream",
                "logs:PutLogEvents"
              ],
              "Resource": "arn:aws:logs:us-east-1:*:*"
            }
          ]
        },
        "Roles": [
          {
            "Ref": "IamRoleLambdaExecution"
          }
        ]
      }
    },
    "SendLambdaFunction": {
      "Type": "AWS::Lambda::Function",
      "Properties": {
        "Code": {
          "S3Bucket": {
            "Ref": "ServerlessDeploymentBucket"
          },
          "S3Key": "serverless/serverless-mailer-rc2/dev/1475828372211-2016-10-07T08:19:32.211Z/serverless-mailer-rc2.zip"
        },
        "FunctionName": "serverless-mailer-rc2-dev-send",
        "Handler": "index.send",
        "MemorySize": 1024,
        "Role": {
          "Fn::GetAtt": [
            "IamRoleLambdaExecution",
            "Arn"
          ]
        },
        "Runtime": "nodejs4.3",
        "Timeout": 6
      }
    }
  },
  "Outputs": {
    "ServerlessDeploymentBucketName": {
      "Value": {
        "Ref": "ServerlessDeploymentBucket"
      }
    },
    "SendLambdaFunctionArn": {
      "Description": "Lambda function info",
      "Value": {
        "Fn::GetAtt": [
          "SendLambdaFunction",
          "Arn"
        ]
      }
    }
  }
}